mbilling/__init__.py
mbilling/client.py
mbilling/object.py
mbilling/resource.py
mbilling_python_sdk-1.0.1.dist-info/LICENSE
mbilling_python_sdk-1.0.1.dist-info/METADATA
mbilling_python_sdk-1.0.1.dist-info/WHEEL
mbilling_python_sdk-1.0.1.dist-info/top_level.txt
mbilling_python_sdk-1.0.1.dist-info/RECORD
