Metadata-Version: 2.1
Name: mbilling-python-sdk
Version: 1.0.1
Summary: Python SDK for the MagnusBilling API
Author: Vertoner
Requires-Python: >=3.6
License-File: LICENSE
